cci_sql_xlsx_converter/sql_to_xlsx.py
cci_sql_xlsx_converter/xlsx_to_sql.py
cci_sql_xlsx_converter-0.3.0.dist-info/METADATA
cci_sql_xlsx_converter-0.3.0.dist-info/WHEEL
cci_sql_xlsx_converter-0.3.0.dist-info/entry_points.txt
cci_sql_xlsx_converter-0.3.0.dist-info/licenses/LICENSE
cci_sql_xlsx_converter-0.3.0.dist-info/RECORD
