Metadata-Version: 2.3
Name: cci_sql_xlsx_converter
Version: 0.3.0
Summary: Old version, pre-name-change. Package is now called "IceTeaCCI" on PyPI. Converts SQL databases generated by Cumulus CI into Excel, for manual editing, and converts them back to SQL files
Project-URL: Repo, https://github.com/ArdenKolodner/CCI-SQL-XLSX-Importer-Exporter
Author-email: Arden Kolodner <akolodner25@amherst.edu>
Classifier: License :: OSI Approved :: MIT License
Classifier: Operating System :: OS Independent
Classifier: Programming Language :: Python :: 3
Requires-Python: >=3.0
Requires-Dist: iceteaccci
Requires-Dist: openpyxl
Requires-Dist: send2trash
